buildbot_react_console_view/VERSION
buildbot_react_console_view/__init__.py
buildbot_react_console_view/static/scripts.js
buildbot_react_console_view/static/styles.css
buildbot_react_console_view-4.0.4.dist-info/METADATA
buildbot_react_console_view-4.0.4.dist-info/WHEEL
buildbot_react_console_view-4.0.4.dist-info/entry_points.txt
buildbot_react_console_view-4.0.4.dist-info/top_level.txt
buildbot_react_console_view-4.0.4.dist-info/RECORD
