Metadata-Version: 2.1
Name: buildbot-react-console-view
Version: 4.0.4
Summary: Buildbot Console View plugin (React)
Home-page: http://buildbot.net/
Author: Pierre Tardy
Author-email: tardyp@gmail.com
Classifier: License :: OSI Approved :: GNU General Public License v2 (GPLv2)
